cryptodataapi/__init__.py
cryptodataapi/binance_api.py
cryptodataapi/bybit_api.py
cryptodataapi-0.0.3.dist-info/METADATA
cryptodataapi-0.0.3.dist-info/WHEEL
cryptodataapi-0.0.3.dist-info/top_level.txt
cryptodataapi-0.0.3.dist-info/RECORD
