Metadata-Version: 2.1
Name: cryptodataapi
Version: 0.0.3
Summary: UNKNOWN
Author: Futurism Labs
Author-email: futurismteam@gmail.com
License: UNKNOWN
Platform: UNKNOWN
Requires-Dist: pandas
Requires-Dist: pybit (==2.3.0)
Requires-Dist: python-binance (==1.0.16)
